odoo/addons/delete_payment_reference_invoice_report/README.rst
odoo/addons/delete_payment_reference_invoice_report/__init__.py
odoo/addons/delete_payment_reference_invoice_report/__manifest__.py
odoo/addons/delete_payment_reference_invoice_report/readme/CONTRIBUTORS.md
odoo/addons/delete_payment_reference_invoice_report/readme/DESCRIPTION.md
odoo/addons/delete_payment_reference_invoice_report/readme/USAGE.md
odoo/addons/delete_payment_reference_invoice_report/report/report_invoice.xml
odoo/addons/delete_payment_reference_invoice_report/static/description/icon.png
odoo/addons/delete_payment_reference_invoice_report/static/description/index.html
odoo_addon_delete_payment_reference_invoice_report-18.0.1.0.0.1.dist-info/METADATA
odoo_addon_delete_payment_reference_invoice_report-18.0.1.0.0.1.dist-info/WHEEL
odoo_addon_delete_payment_reference_invoice_report-18.0.1.0.0.1.dist-info/top_level.txt
odoo_addon_delete_payment_reference_invoice_report-18.0.1.0.0.1.dist-info/RECORD
